mark2pdf/AGENTS.md
mark2pdf/__init__.py
mark2pdf/cli.py
mark2pdf/conversion.py
mark2pdf/defaults.py
mark2pdf/process_builder.py
mark2pdf/commands/__init__.py
mark2pdf/commands/clean.py
mark2pdf/commands/compress.py
mark2pdf/commands/convert.py
mark2pdf/commands/coverimg.py
mark2pdf/commands/fonts.py
mark2pdf/commands/gaozhi.py
mark2pdf/commands/mdimage.py
mark2pdf/commands/version.py
mark2pdf/commands/workspace.py
mark2pdf/config/__init__.py
mark2pdf/config/defaults.py
mark2pdf/config/loader.py
mark2pdf/config/reporter.py
mark2pdf/config/types.py
mark2pdf/config/workspace.py
mark2pdf/core/__init__.py
mark2pdf/core/cli.py
mark2pdf/core/compress.py
mark2pdf/core/core.py
mark2pdf/core/defaults.py
mark2pdf/core/directory.py
mark2pdf/core/options.py
mark2pdf/core/postprocess.py
mark2pdf/core/utils.py
mark2pdf/core/tests/test_cli.py
mark2pdf/core/tests/test_convert_from_string.py
mark2pdf/core/tests/test_core.py
mark2pdf/core/tests/test_force_filename.py
mark2pdf/core/tests/test_output_format.py
mark2pdf/helper_gaozhi/__init__.py
mark2pdf/helper_gaozhi/gaozhi_preprocess.py
mark2pdf/helper_gaozhi/tests/test_gaozhi_preprocess.py
mark2pdf/helper_interfile/__init__.py
mark2pdf/helper_interfile/example_usage.py
mark2pdf/helper_interfile/interfile_manager.py
mark2pdf/helper_interfile/v0.1.1
mark2pdf/helper_interfile/tests/test_interfile_manager.py
mark2pdf/helper_markdown/__init__.py
mark2pdf/helper_markdown/md_preprocess.py
mark2pdf/helper_markdown/sample.md
mark2pdf/helper_markdown/v0.1.6
mark2pdf/helper_markdown/tests/test_extract_frontmatter.py
mark2pdf/helper_markdown/tests/test_pre_add_line_breaks.py
mark2pdf/helper_markdown/tests/test_pre_clean_frontmatter.py
mark2pdf/helper_markdown/tests/test_pre_dash_to_star.py
mark2pdf/helper_markdown/tests/test_pre_for_typst.py
mark2pdf/helper_markdown/tests/test_pre_for_typst_at.py
mark2pdf/helper_markdown/tests/test_pre_for_typst_dollarmark.py
mark2pdf/helper_markdown/tests/test_pre_image_verify.py
yakultpdf-0.7.36.dist-info/METADATA
yakultpdf-0.7.36.dist-info/WHEEL
yakultpdf-0.7.36.dist-info/entry_points.txt
yakultpdf-0.7.36.dist-info/licenses/LICENSE
yakultpdf-0.7.36.dist-info/RECORD
