Metadata-Version: 2.4
Name: yakultpdf
Version: 0.7.36
Summary: Markdown to PDF converter using Pandoc and Typst
Author: mark2pdf contributors
License-Expression: MIT
License-File: LICENSE
Keywords: converter,markdown,pandoc,pdf,typst
Classifier: Development Status :: 4 - Beta
Classifier: Environment :: Console
Classifier: Intended Audience :: Developers
Classifier: License :: OSI Approved :: MIT License
Classifier: Programming Language :: Python :: 3.11
Classifier: Programming Language :: Python :: 3.12
Requires-Python: >=3.11
Requires-Dist: click>=8.0.0
Requires-Dist: markdown-it-py
Requires-Dist: mdit-py-plugins
Requires-Dist: opencc
Requires-Dist: pillow
Requires-Dist: pymupdf
Requires-Dist: pyyaml
Provides-Extra: web
Requires-Dist: fastapi>=0.128.0; extra == 'web'
Requires-Dist: uvicorn[standard]>=0.40.0; extra == 'web'
